{
    "namespace": "MCDenoise",
    "shortalias": "",
    "identifier": "MCDenoise",
    "name": "MCDenoise",
    "type": "PyScript",
    "gpusupport": "",
    "vs_included": 0,
    "url_github": "",
    "url_doom9": "https://forum.doom9.org/showthread.php?t=169782",
    "url_avswiki": "",
    "url_website": "https://bitbucket.org/mystery_keeper/templinearapproximate-vapoursynth",
    "vsrepo": 1,
    "description": "A temporal smoother",
    "deprecated": "",
    "created_at": "2018-09-25 13:07:32",
    "updated_at": "2018-09-25 13:07:32",
    "deleted_at": null,
    "category": "Denoising",
    "functions": [
        {
            "name": "TempLinearApproximateMC",
            "description": "",
            "bitdepth": "unknown",
            "colorspace": "unknown",
            "gpusupport": "",
            "deprecated": "",
            "created_at": "2018-09-25 13:07:32",
            "updated_at": "2018-09-25 13:07:32",
            "deleted_at": null,
            "category": "unknown"
        }
    ]
}